Workbook
Name Brand_List: Lists!$A$2:$A$6
Name Category_List: Lists!$B$2:$B$6
Name Tier_List: Lists!$C$2:$C$5
Name Decision_Rec_List: Lists!$D$2:$D$6
Name Difficulty_Band_List: Lists!$E$2:$E$6
Name Revenue_Band_List: Lists!$F$2:$F$5
Name Public_Viability_List: Lists!$G$2:$G$5
Name Powered_By_AtlasV_List: Lists!$H$2:$H$4
Name Phase_List: Lists!$I$2:$I$8
Name Include_Public_List: Lists!$J$2:$J$4

Sheet Lists
A1: Brand | B1: Category | C1: Tier | D1: Decision_Rec | E1: Difficulty_Band | F1: Revenue_Band | G1: Public_Viability | H1: Powered_By_AtlasV | I1: Phase | J1: Include_in_Public_Site
A2: AtlasForge Games | B2: Game | C2: Core | D2: A — Approve as Primary Canon | E2: Low | F2: Low | G2: High | H2: Yes | I2: Phase 1 — Website + POC + Lite | J2: Yes
A3: AtlasForge Media | B3: Media | C3: Secondary | D3: B — Approve as Secondary Canon | E3: Medium | F3: Medium | G3: Medium | H3: No | I3: Phase 2 — OIA + Media Launch | J3: No
A4: AtlasForge Studio | B4: Studio Tool | C4: Stretch | D4: C — Approve as Stretch Goal | E4: Medium-High | F4: High | G4: Niche | H4: Maybe | I4: Phase 3 — NW + Merch + VoiceForge | J4: Later
A5: Atlas Engine & Atlas-V | B5: Engine / R&D | C5: R&D only | D5: D — Defer | E5: High | F5: Very High | G5: Internal-only | I5: Phase 4 — Hypercasual Pipeline
A6: AtlasForge Merch | B6: Merch | D6: E — Deny | E6: Very High | I6: Phase 5 — Engine Deepening
I7: Phase 6 — Full Studio Product
I8: Phase 7 — Autonomous Systems

Sheet Universe_Index
A1: ID | B1: Name | C1: Brand | D1: Category | E1: Tier | F1: Short_Description | G1: Powered_By_AtlasV | H1: Phase_Planned | I1: Phase_Alt | J1: Status | K1: Notes_Internal | L1: Public_Tagline | M1: Include_in_Public_Site
A2: G-OIA | B2: Octopus in Action | C2: AtlasForge Games | D2: Game | E2: Core | F2: Cozy civic-management sim where Mayor Octavius delegates work via mail and departments. | G2: Yes | H2: Phase 2 — OIA + Media Launch | I2: Phase 5 — Engine deepening | J2: Idea | K2: Flagship game IP; keep canon tight and cozy. | L2: A governed, cozy civic sim powered by Atlas-V.
A3: G-NW | B3: Neighborhood Watch | C3: AtlasForge Games | D3: Game | E3: Core | F3: Serious-feeling police sim where you gradually realize you’re 'only' neighborhood watch. | G3: Yes | H3: Phase 3 — NW + Merch + VoiceForge | I3: Phase 4 — Hypercasual Pipeline | J3: Idea | K3: Leans on comedy in lore, but plays like a grounded sim. | L3: A grounded patrol sim with an increasingly absurd neighborhood reality.
A4: M-FILM | B4: FilmForge | C4: AtlasForge Media | D4: Media | E4: Core | F4: Documentary and educational label for long-form explainers and series. | G4: Yes | H4: Phase 2 — OIA + Media Launch | I4: Phase 3 — NW + Merch + VoiceForge | J4: Idea | K4: Primary non-fiction media arm; system explainers and docs. | L4: Cinematic documentaries and explainers powered by Atlas-V-assisted research.
A5: T-STUDIOPOC | B5: Atlas Studio POC | C5: AtlasForge Studio | D5: Studio Tool | E5: Core | F5: Proof-of-concept creator surface (web + spreadsheet-like) guided by Atlas-V. | G5: Yes | H5: Phase 1 — Website + POC + Lite | I5: Phase 5 — Engine deepening | J5: In Design | K5: Internal POC for future full studio; keep public copy honest but confident. | L5: The first Atlas Studio prototype, powered by Atlas-V and Atlas Engine governance.
A8: G-DD | B8: D/D | C8: AtlasForge Games | D8: Game | E8: Secondary | F8: Tabletop-inspired RPG where the computer GM runs campaigns for you or you GM for AI players. | G8: Yes | H8: Phase 3 — NW + Merch + VoiceForge | J8: Idea | K8: Retro-lite pixel RPG with automated GM tools; long-term franchise potential. | L8: A cozy, rules-light RPG where the 'computer GM' runs the table for you.
A9: G-CONQ | B9: Conquest | C9: AtlasForge Games | D9: Game | E9: Secondary | F9: Real-time strategy game inspired by classic Command & Conquer and Age of Empires. | G9: Yes | H9: Phase 5 — Engine Deepening | J9: Idea | K9: Large-scale RTS showcase title for AtlasForge; ideal for mod support. | L9: A bold RTS about building bases, commanding armies, and outsmarting rival empires.
A10: G-FEUD | B10: Feud | C10: AtlasForge Games | D10: Game | E10: Secondary | F10: Action-RPG inspired by classic Flash-era Feudalism 2 with modern progression. | G10: Yes | H10: Phase 4 — Hypercasual Pipeline | J10: Idea | K10: Mid-scope action-RPG that can reuse systems from other titles. | L10: A fast-moving action-RPG where you grow a tiny warband into a roaming legend.
A11: G-RUN | B11: Runners | C11: AtlasForge Games | D11: Game | E11: Stretch | F11: Hypercasual runner template built to support many reskinned variants. | G11: Yes | H11: Phase 4 — Hypercasual Pipeline | J11: Idea | K11: Backbone for multiple quick-launch mobile runners. | L11: A slick, replayable runner built to spawn an entire line of themed spin-offs.
A12: G-AAB | B12: All A Board | C12: AtlasForge Games | D12: Game | E12: Stretch | F12: Top-down train management game inspired by Now Boarding, focused on routing and timing. | G12: Yes | H12: Phase 4 — Hypercasual Pipeline | J12: Idea | K12: Great candidate for systems reuse and DLC routes. | L12: A charming dispatch sim where you keep trains on time and passengers (mostly) happy.
A13: G-LBTW | B13: Let’s Build the World | C13: AtlasForge Games | D13: Game | E13: Core | F13: God-sim / world builder where you shape continents, guide civilizations, and grow religions over ages. | G13: Yes | H13: Phase 6 — Full Studio Product | J13: Idea | K13: Flagship long-horizon sim with huge expansion potential. | L13: A sweeping god-sim where your choices sculpt continents, cultures, and the flow of history.
A14: G-AUTO | B14: Relayworks | C14: AtlasForge Games | D14: Game | E14: Secondary | F14: Factory/automation builder focused on grounded, earth-like logistics rather than sci-fi. | G14: Yes | H14: Phase 5 — Engine Deepening | J14: Idea | K14: Deep systems sandbox; perfect to stress-test Atlas-V planning logic. | L14: An automation sandbox about building beautiful, efficient production chains on a living world.
A15: M-COM | B15: ComedyForge | C15: AtlasForge Media | D15: Media | E15: Secondary | F15: Comedy-focused content brand for sketches, commentary, and faceless humor formats. | G15: Yes | H15: Phase 2 — OIA + Media Launch | J15: Idea | K15: Primary outlet for light, evergreen comedic content. | L15: A faceless comedy studio for sketches, bits, and running jokes across the AtlasForge universe.
A16: M-STORY | B16: StoryForge | C16: AtlasForge Media | D16: Media | E16: Core | F16: Long-form narrative and true-crime style documentaries with an educational angle. | G16: Yes | H16: Phase 2 — OIA + Media Launch | J16: Idea | K16: Core media pillar; ties into game worlds and real-world topics. | L16: An atmospheric doc series blending careful research with cinematic storytelling.
A17: M-SHORT | B17: AtlasForge Shorts | C17: AtlasForge Media | D17: Media | E17: Secondary | F17: Short-form vertical videos that tease games, media projects, and behind-the-scenes pipelines. | G17: Yes | H17: Phase 3 — NW + Merch + VoiceForge | J17: Idea | K17: Low-cost awareness funnel for all brands. | L17: A fast-moving stream of clips, sneak peeks, and tiny experiments from the AtlasForge lab.
A18: T-VOICE | B18: VoiceForge | C18: AtlasForge Studio | D18: Studio Tool | E18: Secondary | F18: Lightweight voice and performance lab for creating consistent brand voices and NPC delivery. | G18: Yes | H18: Phase 3 — NW + Merch + VoiceForge | J18: Idea | K18: Supports games, media, and trailers; limited lines per run for control. | L18: A small but powerful voice lab for character reads, trailers, and narration tests.
A19: T-HYPER | B19: Hypercasual Forge | C19: AtlasForge Studio | D19: Studio Tool | E19: Stretch | F19: Internal toolkit for designing and shipping small runner-style and tapper games quickly. | G19: Yes | H19: Phase 4 — Hypercasual Pipeline | J19: Idea | K19: Enables many small experiments off one core framework. | L19: A productionline for tiny, punchy hypercasual games spun from shared systems.
... A28: MC-ATLASV | B28: Atlas-V Signal Line | C28: AtlasForge Merch | D28: Merch | E28: Stretch | F28: Minimalist, signal-style merch featuring Atlas-V motifs, diagrams, and process icons. | G28: No | H28: Phase 5 — Engine Deepening | J28: Idea | K28: Targets tech-forward fans and creators. | L28: Sharp, minimal designs inspired by Atlas-V’s lattice, flows, and decision loops.
A29: M-FORGE | B29: FilmForge Documentary Line | C29: AtlasForge Media | D29: Media | E29: Secondary | F29: Long-form AI-assisted documentaries | G29: Yes | H29: Phase 2 | J29: Idea | L29: Premium doc series powered by Atlas-V
A30: S-TOOL1 | B30: Atlas Template Factory | C30: AtlasForge Studio | D30: Studio Tool | E30: Secondary | F30: Marketplace for templates/assets | G30: Yes | H30: Phase 3 | J30: Idea | L30: Creator tools & template marketplace
A31: M-LORE | B31: LoreForge | C31: AtlasForge Media | D31: Media | E31: Secondary | F31: Deep-dive lore and worldbuilding series that stitches together Octopus in Action, Neighborhood Watch, and future IP into a shared AtlasForge universe. | G31: Yes | H31: Phase 2 — OIA + Media Launch | J31: Idea | K31: Internal lore lab brand that can support both marketing content and in‑game canon docs. | L31: Lore-focused videos and articles exploring the stories behind AtlasForge worlds.
A32: M-EDU | B32: AtlasForge Academy | C32: AtlasForge Media | D32: Media | E32: Secondary | F32: Educational, faceless long-form explainers and mini-series about game design, simulation, narrative, and creative tooling. | G32: Yes | H32: Phase 2 — OIA + Media Launch | J32: Idea | K32: Acts as the educational wing of AtlasForge, reusing real project work as case studies. | L32: Structured explainers and series that teach through real AtlasForge projects.
A33: S-MERCH-AUTO | B33: MerchForge Autopilot | C33: AtlasForge Studio | D33: Studio Tool | E33: Stretch | F33: Atlas Studio presets and flows to turn existing art, logos, and characters into ready-to-print merch briefs and packs. | G33: Yes | H33: Phase 3 — NW + Merch + VoiceForge | J33: Idea | K33: Bridges in-game art and print-on-demand vendors with minimal extra work. | L33: A small Studio-side tool that makes spinning up new merch designs fast and consistent.
A34: S-DOCPIPE | B34: DocForge Pipeline | C34: AtlasForge Studio | D34: Studio Tool | E34: Stretch | F34: Repeatable documentary and educational video workflow: research, outline, script, shot list, and delivery checklists. | G34: Yes | H34: Phase 3 — NW + Merch + VoiceForge | J34: Idea | K34: Internal production pipeline backing FilmForge and Academy content. | L34: Template-driven doc production inside Atlas Studio POC.
A35: E-CHANNEL | B35: Channel Engine | C35: Atlas Engine & Atlas-V | D35: Engine / R&D | E35: R&D only | F35: Atlas Engine extensions for orchestrating content calendars, prompts, and review loops across multiple media brands. | G35: Yes | H35: Phase 7 — Autonomous Systems | J35: Idea | K35: Backbone for semi-automated but human-reviewed channels rather than pure firehose automation. | L35: Internal orchestration layer that quietly powers FilmForge, Academy, Shorts, and more.
A36: E-GAMEGEN | B36: Hypercasual Design Forge | C36: Atlas Engine & Atlas-V | D36: Engine / R&D | E36: R&D only | F36: Internal design pipeline to generate repeatable design docs and asset briefs for runner-style and hypercasual games. | G36: Yes | H36: Phase 4 — Hypercasual Pipeline | J36: Idea | K36: Treats runners and similar games as a content format that Atlas Engine can help spec repeatedly. | L36: A design factory that feeds the Hypercasual Runner slate, not a one-click game generator.
A37: R-AUTOCHANNEL | B37: Autonomous Channel Lab | C37: Atlas Engine & Atlas-V | D37: Engine / R&D | E37: R&D only | F37: Sandbox for experimenting with higher-automation content loops under strict governance and review. | G37: Yes | H37: Phase 7 — Autonomous Systems | J37: Idea | K37: Internal testing ground only; never marketed directly as a product. | L37: Long-horizon lab project exploring safe semi-autonomous creative systems.
A38: R-DOCGEN | B38: Narrative Blueprint Lab | C38: Atlas Engine & Atlas-V | D38: Engine / R&D | E38: R&D only | F38: R&D space for scenario templates, narrative structures, and modular quest/dialogue patterns for future projects. | G38: Yes | H38: Phase 5 — Engine Deepening | J38: Idea | K38: Helps future games and media share a library of reusable narrative structures without feeling copy-pasted. | L38: Internal storytelling lab to keep AtlasForge worlds coherent and flexible.

Sheet Canon_Matrix
A1: ID | B1: Name | C1: Difficulty_Band | D1: Revenue_Band | E1: Public_Viability | F1: Audience_Segment | G1: Platform_Type | H1: Internal_Only_Components | I1: Dependencies | J1: AtlasV_Usage_Notes | K1: Risk_Notes
A2: G-OIA | B2: Octopus in Action | C2: Medium-High | D2: High | E2: High | F2: Cozy management & sim players | G2: PC / Console | H2: Internal: task-routing rules, department scheduling logic. | I2: Requires Atlas-V, Studio POC. | J2: Drives daily loops, coaching player decisions. | K2: Scope creep risk; must remain cozy and legible.
A3: G-NW | B3: Neighborhood Watch | C3: High | D3: High | E3: High | F3: Fans of police sims and satire | G3: PC / Console | H3: Internal: tone guardrails, escalation rules. | I3: Requires narrative tools, tone guardrails. | J3: Helps generate and triage call scenarios. | K3: Tone is sensitive; must be carefully governed.
A4: M-FILM | B4: FilmForge | C4: Medium | D4: Medium-High | E4: High | F4: Viewers of docs and explainers | G4: Web / Streaming | H4: Internal: automated pipelines not public. | I4: Needs media toolchain, rights mgmt. | J4: Assists with research, outlines, and continuity. | K4: Rights, research, and QA are key risks.
A5: T-STUDIOPOC | B5: Atlas Studio POC | C5: Medium-High | D5: High | E5: Internal-only | F5: Internal/external creators in tests | G5: Web | H5: Internal orchestration, governance surfaces. | I5: Requires Atlas Engine, Atlas-V. | J5: Central orchestrator for workflows and prompts. | K5: UX complexity; must stay legible.
A21: G-DD | B21: D/D | C21: Medium-High | D21: High | E21: High | F21: PC & console gamers | G21: PC (Steam) first, possible console later
A22: G-CONQ | B22: Conquest | C22: Medium-High | D22: High | E22: High | F22: RTS / strategy players | G22: PC (Steam) first, possible console later
A23: G-FEUD | B23: Feud | C23: Medium-High | D23: High | E23: High | F23: PC & console gamers | G23: PC (Steam) first, possible console later
A24: G-RUN | B24: Runners | C24: Medium-High | D24: Medium | E24: High | F24: PC & console gamers | G24: PC (Steam) first, possible console later
A25: G-AAB | B25: All A Board | C25: Medium-High | D25: Medium | E25: High | F25: PC & console gamers | G25: PC (Steam) first, possible console later
A26: G-LBTW | B26: Let’s Build the World | C26: High | D26: High | E26: High | F26: PC & console gamers | G26: PC (Steam) first, possible console later
A27: G-AUTO | B27: Relayworks | C27: Medium-High | D27: High | E27: High | F27: PC & console gamers | G27: PC (Steam) first, possible console later
A28: M-COM | B28: ComedyForge | C28: Medium | D28: Medium | E28: High | F28: Viewers of long-form educational & commentary content | G28: YouTube / streaming
A29: M-STORY | B29: StoryForge | C29: Medium | D29: High | E29: High | F29: Viewers of long-form educational & commentary content | G29: YouTube / streaming
A30: M-SHORT | B30: AtlasForge Shorts | C30: Medium | D30: Medium | E30: High | F30: Viewers of long-form educational & commentary content | G30: YouTube / streaming
A31: T-VOICE | B31: VoiceForge | C31: Medium-High | D31: High | E31: High | F31: Creators using Atlas Studio | G31: Web + desktop
A32: T-HYPER | B32: Hypercasual Forge | C32: Medium | D32: High | E32: High | F32: Creators using Atlas Studio | G32: Web + desktop
... A51: R-DOCGEN | B51: Narrative Blueprint Lab | C51: Very High | D51: High | E51: Niche | F51: Internal devs / advanced partners | G51: Web + desktop

Sheet Decision_Table
A1: ID | B1: Name | C1: Brand | D1: Category | E1: Rec_Decision | F1: Your_Decision | G1: Reason_Note | H1: Phase_Assigned | I1: Include_in_Public_Site | J1: Priority_Score
A2: G-OIA | B2: Octopus in Action | C2: AtlasForge Games | D2: Game | E2: A — Approve as Primary Canon | H2: Phase 2 — OIA + Media Launch | I2: =IF(F2="A — Approve as Primary Canon",5,IF(F2="B — Approve as Secondary Canon",4,IF(F2="C — Approve as Stretch Goal",3,IF(F2="D — Defer",2,IF(F2="E — Deny",1,0))))) | J2: =IF(F2="A — Approve as Primary Canon",5, IF(F2="B — Approve as Secondary Canon",4, IF(F2="C — Approve as Stretch Goal",3, IF(F2="D — Defer",2, IF(F2="E — Deny",1,0)))))
A3: G-NW | B3: Neighborhood Watch | C3: AtlasForge Games | D3: Game | E3: A — Approve as Primary Canon | H3: Phase 3 — NW + Merch + VoiceForge | I3: =IF(F3="A — Approve as Primary Canon",5,IF(F3="B — Approve as Secondary Canon",4,IF(F3="C — Approve as Stretch Goal",3,IF(F3="D — Defer",2,IF(F3="E — Deny",1,0))))) | J3: =IF(F3="A — Approve as Primary Canon",5, IF(F3="B — Approve as Secondary Canon",4, IF(F3="C — Approve as Stretch Goal",3, IF(F3="D — Defer",2, IF(F3="E — Deny",1,0)))))
A4: M-FILM | B4: FilmForge | C4: AtlasForge Media | D4: Media | E4: A — Approve as Primary Canon | H4: Phase 2 — OIA + Media Launch | I4: =IF(F4="A — Approve as Primary Canon",5,IF(F4="B — Approve as Secondary Canon",4,IF(F4="C — Approve as Stretch Goal",3,IF(F4="D — Defer",2,IF(F4="E — Deny",1,0))))) | J4: =IF(F4="A — Approve as Primary Canon",5, IF(F4="B — Approve as Secondary Canon",4, IF(F4="C — Approve as Stretch Goal",3, IF(F4="D — Defer",2, IF(F4="E — Deny",1,0)))))
A5: T-STUDIOPOC | B5: Atlas Studio POC | C5: AtlasForge Studio | D5: Studio Tool | E5: A — Approve as Primary Canon | H5: Phase 1 — Website + POC + Lite | I5: =IF(F5="A — Approve as Primary Canon",5,IF(F5="B — Approve as Secondary Canon",4,IF(F5="C — Approve as Stretch Goal",3,IF(F5="D — Defer",2,IF(F5="E — Deny",1,0))))) | J5: =IF(F5="A — Approve as Primary Canon",5, IF(F5="B — Approve as Secondary Canon",4, IF(F5="C — Approve as Stretch Goal",3, IF(F5="D — Defer",2, IF(F5="E — Deny",1,0)))))
A6: G-DD | B6: D/D | C6: AtlasForge Games | D6: Game | E6: B — Approve as Secondary Canon | H6: Phase 4 — Hypercasual Pipeline | I6: =IF(F6="A — Approve as Primary Canon",5,IF(F6="B — Approve as Secondary Canon",4,IF(F6="C — Approve as Stretch Goal",3,IF(F6="D — Defer",2,IF(F6="E — Deny",1,0))))) | J6: =IF(F6="A — Approve as Primary Canon",5, IF(F6="B — Approve as Secondary Canon",4, IF(F6="C — Approve as Stretch Goal",3, IF(F6="D — Defer",2, IF(F6="E — Deny",1,0)))))
A7: G-CONQ | B7: Conquest | C7: AtlasForge Games | D7: Game | E7: B — Approve as Secondary Canon | H7: Phase 4 — Hypercasual Pipeline | I7: =IF(F7="A — Approve as Primary Canon",5,IF(F7="B — Approve as Secondary Canon",4,IF(F7="C — Approve as Stretch Goal",3,IF(F7="D — Defer",2,IF(F7="E — Deny",1,0))))) | J7: =IF(F7="A — Approve as Primary Canon",5, IF(F7="B — Approve as Secondary Canon",4, IF(F7="C — Approve as Stretch Goal",3, IF(F7="D — Defer",2, IF(F7="E — Deny",1,0)))))
A8: G-FEUD | B8: Feud | C8: AtlasForge Games | D8: Game | E8: B — Approve as Secondary Canon | H8: Phase 4 — Hypercasual Pipeline | I8: =IF(F8="A — Approve as Primary Canon",5,IF(F8="B — Approve as Secondary Canon",4,IF(F8="C — Approve as Stretch Goal",3,IF(F8="D — Defer",2,IF(F8="E — Deny",1,0))))) | J8: =IF(F8="A — Approve as Primary Canon",5, IF(F8="B — Approve as Secondary Canon",4, IF(F8="C — Approve as Stretch Goal",3, IF(F8="D — Defer",2, IF(F8="E — Deny",1,0)))))
A9: G-RUN | B9: Runners | C9: AtlasForge Games | D9: Game | E9: C — Approve as Stretch Goal | H9: Phase 4 — Hypercasual Pipeline | I9: =IF(F9="A — Approve as Primary Canon",5,IF(F9="B — Approve as Secondary Canon",4,IF(F9="C — Approve as Stretch Goal",3,IF(F9="D — Defer",2,IF(F9="E — Deny",1,0))))) | J9: =IF(F9="A — Approve as Primary Canon",5, IF(F9="B — Approve as Secondary Canon",4, IF(F9="C — Approve as Stretch Goal",3, IF(F9="D — Defer",2, IF(F9="E — Deny",1,0)))))
A10: G-AAB | B10: All A Board | C10: AtlasForge Games | D10: Game | E10: C — Approve as Stretch Goal | H10: Phase 4 — Hypercasual Pipeline | I10: =IF(F10="A — Approve as Primary Canon",5,IF(F10="B — Approve as Secondary Canon",4,IF(F10="C — Approve as Stretch Goal",3,IF(F10="D — Defer",2,IF(F10="E — Deny",1,0))))) | J10: =IF(F10="A — Approve as Primary Canon",5, IF(F10="B — Approve as Secondary Canon",4, IF(F10="C — Approve as Stretch Goal",3, IF(F10="D — Defer",2, IF(F10="E — Deny",1,0)))))
A11: G-LBTW | B11: Let’s Build the World | C11: AtlasForge Games | D11: Game | E11: A — Approve as Primary Canon | H11: Phase 5 — Engine Deepening | I11: =IF(F11="A — Approve as Primary Canon",5,IF(F11="B — Approve as Secondary Canon",4,IF(F11="C — Approve as Stretch Goal",3,IF(F11="D — Defer",2,IF(F11="E — Deny",1,0))))) | J11: =IF(F11="A — Approve as Primary Canon",5, IF(F11="B — Approve as Secondary Canon",4, IF(F11="C — Approve as Stretch Goal",3, IF(F11="D — Defer",2, IF(F11="E — Deny",1,0)))))
A12: G-AUTO | B12: Relayworks | C12: AtlasForge Games | D12: Game | E12: B — Approve as Secondary Canon | H12: Phase 4 — Hypercasual Pipeline | I12: =IF(F12="A — Approve as Primary Canon",5,IF(F12="B — Approve as Secondary Canon",4,IF(F12="C — Approve as Stretch Goal",3,IF(F12="D — Defer",2,IF(F12="E — Deny",1,0))))) | J12: =IF(F12="A — Approve as Primary Canon",5, IF(F12="B — Approve as Secondary Canon",4, IF(F12="C — Approve as Stretch Goal",3, IF(F12="D — Defer",2, IF(F12="E — Deny",1,0)))))
A13: M-COM | B13: ComedyForge | C13: AtlasForge Media | D13: Media | E13: B — Approve as Secondary Canon | H13: Phase 4 — Hypercasual Pipeline | I13: =IF(F13="A — Approve as Primary Canon",5,IF(F13="B — Approve as Secondary Canon",4,IF(F13="C — Approve as Stretch Goal",3,IF(F13="D — Defer",2,IF(F13="E — Deny",1,0))))) | J13: =IF(F13="A — Approve as Primary Canon",5, IF(F13="B — Approve as Secondary Canon",4, IF(F13="C — Approve as Stretch Goal",3, IF(F13="D — Defer",2, IF(F13="E — Deny",1,0)))))
... A36: R-DOCGEN | B36: Narrative Blueprint Lab | C36: Atlas Engine & Atlas-V | D36: Engine / R&D | E36: D — Defer | H36: Phase 7 — Autonomous Systems | I36: =IF(F36="A — Approve as Primary Canon",5,IF(F36="B — Approve as Secondary Canon",4,IF(F36="C — Approve as Stretch Goal",3,IF(F36="D — Defer",2,IF(F36="E — Deny",1,0))))) | J36: =IF(F36="A — Approve as Primary Canon",5, IF(F36="B — Approve as Secondary Canon",4, IF(F36="C — Approve as Stretch Goal",3, IF(F36="D — Defer",2, IF(F36="E — Deny",1,0)))))

Sheet Roadmap
C2: =COUNTIFS(Decision_Table!H:H,A2,Decision_Table!F:F,"<>E — Deny") | D2: =COUNTIFS(Decision_Table!H:H,A2,Decision_Table!F:F,"A — Approve as Primary Canon") | E2: =COUNTIFS(Decision_Table!H:H,A2,Decision_Table!F:F,"C — Approve as Stretch Goal")
C3: =COUNTIFS(Decision_Table!H:H,A3,Decision_Table!F:F,"<>E — Deny") | D3: =COUNTIFS(Decision_Table!H:H,A3,Decision_Table!F:F,"A — Approve as Primary Canon") | E3: =COUNTIFS(Decision_Table!H:H,A3,Decision_Table!F:F,"C — Approve as Stretch Goal")
C4: =COUNTIFS(Decision_Table!H:H,A4,Decision_Table!F:F,"<>E — Deny") | D4: =COUNTIFS(Decision_Table!H:H,A4,Decision_Table!F:F,"A — Approve as Primary Canon") | E4: =COUNTIFS(Decision_Table!H:H,A4,Decision_Table!F:F,"C — Approve as Stretch Goal")
C5: =COUNTIFS(Decision_Table!H:H,A5,Decision_Table!F:F,"<>E — Deny") | D5: =COUNTIFS(Decision_Table!H:H,A5,Decision_Table!F:F,"A — Approve as Primary Canon") | E5: =COUNTIFS(Decision_Table!H:H,A5,Decision_Table!F:F,"C — Approve as Stretch Goal")
C6: =COUNTIFS(Decision_Table!H:H,A6,Decision_Table!F:F,"<>E — Deny") | D6: =COUNTIFS(Decision_Table!H:H,A6,Decision_Table!F:F,"A — Approve as Primary Canon") | E6: =COUNTIFS(Decision_Table!H:H,A6,Decision_Table!F:F,"C — Approve as Stretch Goal")
C7: =COUNTIFS(Decision_Table!H:H,A7,Decision_Table!F:F,"<>E — Deny") | D7: =COUNTIFS(Decision_Table!H:H,A7,Decision_Table!F:F,"A — Approve as Primary Canon") | E7: =COUNTIFS(Decision_Table!H:H,A7,Decision_Table!F:F,"C — Approve as Stretch Goal")
C8: =COUNTIFS(Decision_Table!H:H,A8,Decision_Table!F:F,"<>E — Deny") | D8: =COUNTIFS(Decision_Table!H:H,A8,Decision_Table!F:F,"A — Approve as Primary Canon") | E8: =COUNTIFS(Decision_Table!H:H,A8,Decision_Table!F:F,"C — Approve as Stretch Goal")
A51: Phase | B51: Description | C51: Planned_Projects_Count | D51: Core_Projects_Count | E51: Stretch_Projects_Count | F51: Notes
A52: Phase 1 — Website + POC + Lite | B52: Website, Atlas Studio POC, Atlas-V Lite foundation.
A53: Phase 2 — OIA + Media Launch | B53: Octopus in Action plus FilmForge/Media pilots.
A54: Phase 3 — NW + Merch + VoiceForge | B54: Neighborhood Watch, initial merch, and voice tools.
A55: Phase 4 — Hypercasual Pipeline | B55: Runners and simple mini-game production systems.
A56: Phase 5 — Engine Deepening | B56: Atlas Engine and Atlas-V refinement and integrations.
A57: Phase 6 — Full Studio Product | B57: Atlas Studio graduates from POC to product.
A58: Phase 7 — Autonomous Systems | B58: High automation and self-updating pipelines.

Sheet Brands
A1: Brand | B1: Identity | C1: Tone | D1: Core_Audience | E1: Canon_Themes | F1: What_to_Avoid | G1: Example_Projects | H1: Revenue_Streams
A2: AtlasForge Games | B2: Multi-genre game label spanning cozy sims, serious strategy, and experimental titles. | C2: Playful, confident, craft-focused; never cynical. | D2: Players who like depth, charm, and thoughtful systems. | E2: World-driven IP, strong systems, replayable loops. | F2: Low-effort cash-grabs, predatory monetization, shallow clones. | G2: Octopus in Action, Neighborhood Watch, D/D, Conquest. | H2: Premium purchases, DLC/expansions, bundles, OSTs.
A3: AtlasForge Media | B3: Documentary and educational storytelling arm for systems, history, and culture. | C3: Warm, curious, respectful, occasionally witty. | D3: Learners, documentary fans, curious general audience. | E3: Clarity, empathy, strong research, human-centered angles. | F3: Sensationalism, exploitative true crime framing, cheap clickbait. | G3: FilmForge series, ComedyForge commentary, StoryForge narratives. | H3: Streaming revenue, sponsorships, companion books, licensing.
A4: AtlasForge Studio | B4: Tools, templates, and workspaces that help creators think, plan, and build. | C4: Supportive, practical, quietly clever. | D4: Indie devs, small teams, solo creators, operations nerds. | E4: Reducing friction, clarifying thinking, reusable patterns. | F4: Bloated enterprise bloatware vibes, unnecessary complexity. | G4: Atlas Studio POC, TemplateBuilder, VoiceForge, SoundForge. | H4: Licensing, subscriptions, template packs.
A5: Atlas Engine & Atlas-V | B5: Governed logic core and project copilot powering AtlasForge’s tools and outputs. | C5: Precise, clear, reliable; the grown-up in the room. | D5: Internal teams, advanced users, future external partners. | E5: Safety, structure, constraint-respect, cross-project memory. | F5: Overpromising AGI magic tricks, opaque behavior. | G5: Atlas Engine governance, Atlas-V copilot, Atlas-V Lite GPT experiences. | H5: Indirect: enables everything else to make money; possible future API access.
A6: AtlasForge Merch | B6: Physical and digital goods that extend the worlds and aesthetics of the brand. | C6: Fun, collectible, slightly mischievous. | D6: Fans of the games, media, and studio aesthetic. | E6: Delight, quality, in-jokes tied to canon, cozy loyalty. | F6: Cheap-feeling print-on-demand spam, off-brand memes. | G6: ForgeWear apparel, Pixel Plush (OIA), Real Horse Unit gag line. | H6: Per-item sales, limited drops, bundles tied to releases.

Sheet Summary
A1: Metric | B1: Value
A2: Total Projects | B2: =ROWS(Universe_Index!A:A)-1
A3: Games Count | B3: =COUNTIF(Universe_Index!C:C,"AtlasForge Games")
A4: Media Count | B4: =COUNTIF(Universe_Index!C:C,"AtlasForge Media")
A5: Studio Tools Count | B5: =COUNTIF(Universe_Index!C:C,"AtlasForge Studio")
A6: Engine/R&D Count | B6: =COUNTIF(Universe_Index!C:C,"Atlas Engine & Atlas-V")
A7: Merch Count | B7: =COUNTIF(Universe_Index!C:C,"AtlasForge Merch")
A9: Primary Canon (A) Count | B9: =COUNTIF(Decision_Table!F:F,"A — Approve as Primary Canon")
A10: Secondary Canon (B) Count | B10: =COUNTIF(Decision_Table!F:F,"B — Approve as Secondary Canon")
A11: Stretch (C) Count | B11: =COUNTIF(Decision_Table!F:F,"C — Approve as Stretch Goal")
A12: Deferred (D) Count | B12: =COUNTIF(Decision_Table!F:F,"D — Defer")
A13: Denied (E) Count | B13: =COUNTIF(Decision_Table!F:F,"E — Deny")

Sheet Instructions
A1: AtlasForge Master Canon Workbook (v1) This workbook is designed to track all AtlasForge projects (games, media, tools, engine, merch, R&D) and your canon decisions. Basic usage order: 1) Fill out Universe_Index with one row per project/IP/tool. 2) Use Canon_Matrix to add difficulty, revenue, audience, and risk notes. 3) Use Decision_Table to assign A/B/C/D/E and roadmap phases. 4) Review Roadmap and Summary to see how phases and priorities stack up. 5) Use Brands to keep track of each brand's identity, tone, and revenue patterns. The Lists sheet is for dropdown values and should normally stay hidden.
